pyhems/__init__.py
pyhems/const.py
pyhems/definitions.json
pyhems/definitions.py
pyhems/discovery.py
pyhems/eoj.py
pyhems/frame.py
pyhems/py.typed
pyhems/runtime.py
pyhems/transport.py
pyhems/utils.py
pyhems-0.2.0.dist-info/licenses/LICENSE
pyhems-0.2.0.dist-info/METADATA
pyhems-0.2.0.dist-info/WHEEL
pyhems-0.2.0.dist-info/top_level.txt
pyhems-0.2.0.dist-info/RECORD
