Metadata-Version: 2.4
Name: pyhems
Version: 0.2.0
Summary: ECHONET Lite library for Home Energy Management System (HEMS)
Author: Sayurin
License-Expression: MIT
Classifier: Development Status :: 3 - Alpha
Classifier: Intended Audience :: Developers
Classifier: Operating System :: OS Independent
Classifier: Programming Language :: Python :: 3
Classifier: Programming Language :: Python :: 3.13
Requires-Python: >=3.13
License-File: LICENSE
Requires-Dist: bidict>=0.23.0
Provides-Extra: dev
Requires-Dist: pytest>=7.0; extra == "dev"
Requires-Dist: pytest-asyncio>=0.21; extra == "dev"
Requires-Dist: pytest-cov>=4.0; extra == "dev"
Dynamic: license-file
